dreadnode_cli/__init__.py
dreadnode_cli/__main__.py
dreadnode_cli/agent/__init__.py
dreadnode_cli/agent/cli.py
dreadnode_cli/agent/config.py
dreadnode_cli/agent/docker.py
dreadnode_cli/agent/format.py
dreadnode_cli/agent/templates/__init__.py
dreadnode_cli/agent/templates/cli.py
dreadnode_cli/agent/templates/format.py
dreadnode_cli/agent/templates/manager.py
dreadnode_cli/agent/tests/__init__.py
dreadnode_cli/agent/tests/test_cli.py
dreadnode_cli/agent/tests/test_config.py
dreadnode_cli/agent/tests/test_docker.py
dreadnode_cli/agent/tests/test_templates.py
dreadnode_cli/api.py
dreadnode_cli/challenge/__init__.py
dreadnode_cli/challenge/cli.py
dreadnode_cli/cli.py
dreadnode_cli/config.py
dreadnode_cli/defaults.py
dreadnode_cli/ext/typer.py
dreadnode_cli/model/__init__.py
dreadnode_cli/model/cli.py
dreadnode_cli/model/config.py
dreadnode_cli/model/format.py
dreadnode_cli/profile/__init__.py
dreadnode_cli/profile/cli.py
dreadnode_cli/tests/__init__.py
dreadnode_cli/tests/test_api_client.py
dreadnode_cli/tests/test_api_create_client.py
dreadnode_cli/tests/test_api_token.py
dreadnode_cli/tests/test_config.py
dreadnode_cli/tests/test_lib.py
dreadnode_cli/tests/test_types.py
dreadnode_cli/tests/test_utils.py
dreadnode_cli/types.py
dreadnode_cli/utils.py
dreadnode_cli-0.2.2.dist-info/LICENSE
dreadnode_cli-0.2.2.dist-info/METADATA
dreadnode_cli-0.2.2.dist-info/WHEEL
dreadnode_cli-0.2.2.dist-info/entry_points.txt
dreadnode_cli-0.2.2.dist-info/RECORD
