Metadata-Version: 2.1
Name: dreadnode-cli
Version: 0.2.2
Summary: Dreadnode CLI
Home-page: https://github.com/dreadnode/cli
License: MIT
Author: Nick Landers
Author-email: monoxgas@gmail.com
Requires-Python: >=3.10,<4.0
Classifier: License :: OSI Approved :: MIT License
Classifier: Programming Language :: Python :: 3
Classifier: Programming Language :: Python :: 3.10
Classifier: Programming Language :: Python :: 3.11
Classifier: Programming Language :: Python :: 3.12
Classifier: Programming Language :: Python :: 3.13
Requires-Dist: docker (>=7.1.0,<8.0.0)
Requires-Dist: httpx (>=0.27.2,<0.28.0)
Requires-Dist: jinja2 (>=3.1.4,<4.0.0)
Requires-Dist: pydantic (>=2.9.2,<3.0.0)
Requires-Dist: pydantic-yaml (>=1.4.0,<2.0.0)
Requires-Dist: ruamel-yaml (>=0.18.6,<0.19.0)
Requires-Dist: toml (>=0.10.2,<0.11.0)
Requires-Dist: typer (>=0.12.5,<0.13.0)
Requires-Dist: types-requests (>=2.32.0.20240914,<3.0.0.0)
Requires-Dist: types-toml (>=0.10.8.20240310,<0.11.0.0)
Project-URL: Repository, https://github.com/dreadnode/cli
